xlwt/BIFFRecords.py
xlwt/Bitmap.py
xlwt/Cell.py
xlwt/Column.py
xlwt/CompoundDoc.py
xlwt/ExcelFormula.py
xlwt/ExcelFormulaLexer.py
xlwt/ExcelFormulaParser.py
xlwt/ExcelMagic.py
xlwt/Formatting.py
xlwt/Row.py
xlwt/Style.py
xlwt/UnicodeUtils.py
xlwt/Utils.py
xlwt/Workbook.py
xlwt/Worksheet.py
xlwt/__init__.py
xlwt/antlr.py
xlwt/compat.py
xlwt/excel-formula.g
xlwt-1.1.1.dist-info/DESCRIPTION.rst
xlwt-1.1.1.dist-info/METADATA
xlwt-1.1.1.dist-info/RECORD
xlwt-1.1.1.dist-info/WHEEL
xlwt-1.1.1.dist-info/metadata.json
xlwt-1.1.1.dist-info/top_level.txt
